qontract_development_cli/__init__.py
qontract_development_cli/__main__.py
qontract_development_cli/cli.py
qontract_development_cli/completions.py
qontract_development_cli/config.py
qontract_development_cli/models.py
qontract_development_cli/shell.py
qontract_development_cli/templates.py
qontract_development_cli/utils.py
qontract_development_cli/watchdog.py
qontract_development_cli/commands/__init__.py
qontract_development_cli/commands/config.py
qontract_development_cli/commands/env.py
qontract_development_cli/commands/profile.py
qontract_development_cli/templates/api.yml.j2
qontract_development_cli/templates/cache.yml.j2
qontract_development_cli/templates/compose.override.yml.j2
qontract_development_cli/templates/compose.yml.j2
qontract_development_cli/templates/internal-redhat-ca.yml.j2
qontract_development_cli/templates/prep-worktree.sh.j2
qontract_development_cli/templates/reconcile.yml.j2
qontract_development_cli/templates/server.yml.j2
qontract_development_cli/templates/vault.yml.j2
qontract_development_cli/templates/worker.yml.j2
qontract_development_cli-0.16.0.dist-info/METADATA
qontract_development_cli-0.16.0.dist-info/WHEEL
qontract_development_cli-0.16.0.dist-info/entry_points.txt
qontract_development_cli-0.16.0.dist-info/RECORD
