Metadata-Version: 2.4
Name: qontract-development-cli
Version: 0.16.0
Summary: Helper tool for qontract-reconcile development
Project-URL: homepage, http://github.com/chassing/qontract-development-cli
Project-URL: repository, http://github.com/chassing/qontract-development-cli
Project-URL: documentation, http://github.com/chassing/qontract-development-cli
Author-email: Christian Assing <cassing@redhat.com>
License: MIT
Requires-Python: >=3.11
Requires-Dist: appdirs~=1.4.4
Requires-Dist: getkey~=0.6.5
Requires-Dist: jinja2~=3.1
Requires-Dist: pydantic-settings~=2.6
Requires-Dist: pydantic~=2.9
Requires-Dist: pyyaml~=6.0.2
Requires-Dist: rich~=14.0
Requires-Dist: typer~=0.21.0
Requires-Dist: watchfiles~=1.1.0
